exposedfunctionality/__init__.py
exposedfunctionality/func.py
exposedfunctionality/function_parser/__init__.py
exposedfunctionality/function_parser/custom_wrapper.py
exposedfunctionality/function_parser/docstring_parser.py
exposedfunctionality/function_parser/function_parser.py
exposedfunctionality/function_parser/ser_types.py
exposedfunctionality/function_parser/types.py
exposedfunctionality/variables/__init__.py
exposedfunctionality/variables/core.py
exposedfunctionality/variables/middleware.py
exposedfunctionality-1.0.3.dist-info/METADATA
exposedfunctionality-1.0.3.dist-info/WHEEL
exposedfunctionality-1.0.3.dist-info/licenses/LICENSE
exposedfunctionality-1.0.3.dist-info/RECORD
