Metadata-Version: 2.4
Name: exposedfunctionality
Version: 1.0.3
Summary: tool to expose functionalities to multiple tools
Project-URL: Homepage, https://github.com/JulianKimmig/exposedfunctionality
Project-URL: Source, https://github.com/JulianKimmig/exposedfunctionality
Project-URL: Tracker, https://github.com/JulianKimmig/exposedfunctionality/issues
Project-URL: Download, https://pypi.org/project/exposedfunctionality/#files
Author-email: Julian Kimmig <julian.kimmig@linkdlab.de>
License: MIT
License-File: LICENSE
Requires-Python: >=3.11
Requires-Dist: pyyaml
Requires-Dist: typing-extensions
Provides-Extra: dev
Requires-Dist: numpy; extra == 'dev'
Requires-Dist: pre-commit; extra == 'dev'
Requires-Dist: pytest; extra == 'dev'
Requires-Dist: tomli; (python_version < '3.11') and extra == 'dev'
